chat_downloader/__init__.py
chat_downloader/__main__.py
chat_downloader/chat_downloader.py
chat_downloader/cli.py
chat_downloader/debugging.py
chat_downloader/errors.py
chat_downloader/metadata.py
chat_downloader/formatting/__init__.py
chat_downloader/formatting/custom_formats.json
chat_downloader/formatting/format.py
chat_downloader/output/__init__.py
chat_downloader/output/continuous_write.py
chat_downloader/sites/__init__.py
chat_downloader/sites/common.py
chat_downloader/sites/facebook.py
chat_downloader/sites/twitch.py
chat_downloader/sites/youtube.py
chat_downloader/sites/zoom.py
chat_downloader/utils/__init__.py
chat_downloader/utils/core.py
chat_downloader/utils/timed_utils.py
chat_downloader-0.2.8.dist-info/AUTHORS.md
chat_downloader-0.2.8.dist-info/LICENSE
chat_downloader-0.2.8.dist-info/METADATA
chat_downloader-0.2.8.dist-info/WHEEL
chat_downloader-0.2.8.dist-info/entry_points.txt
chat_downloader-0.2.8.dist-info/top_level.txt
chat_downloader-0.2.8.dist-info/RECORD
