Metadata-Version: 2.1
Name: chat-downloader
Version: 0.2.8
Summary: A simple tool used to retrieve chat messages from livestreams, videos, clips and past broadcasts. No authentication needed!
Home-page: https://github.com/xenova/chat-downloader
Author: xenova
Author-email: admin@xenova.com
License: MIT license
Keywords: python chat downloader youtube twitch
Classifier: Development Status :: 4 - Beta
Classifier: Intended Audience :: Developers
Classifier: License :: OSI Approved :: MIT License
Classifier: Natural Language :: English
Classifier: Programming Language :: Python :: 3
Classifier: Programming Language :: Python :: 3.6
Classifier: Programming Language :: Python :: 3.7
Classifier: Programming Language :: Python :: 3.8
Classifier: Programming Language :: Python :: 3.9
Classifier: Programming Language :: Python :: 3.10
Classifier: Operating System :: OS Independent
Requires-Python: >=3.6
Provides-Extra: dev
License-File: LICENSE
License-File: AUTHORS.md
